PySonataWebAPI/__init__.py
PySonataWebAPI/WebAPI/__init__.py
PySonataWebAPI/WebAPI/Client/__init__.py
PySonataWebAPI/WebAPI/Constants/__init__.py
PySonataWebAPI/WebAPI/Interface/__init__.py
PySonataWebAPI/WebAPI/Interface/BankAccounts/__init__.py
PySonataWebAPI/WebAPI/Interface/BankAccounts/Interfaces/__init__.py
PySonataWebAPI/WebAPI/Interface/BankAccounts/Interfaces/IBankAccountsController/__init__.py
PySonataWebAPI/WebAPI/Interface/BankAccounts/ViewModels/__init__.py
PySonataWebAPI/WebAPI/Interface/Common/__init__.py
PySonataWebAPI/WebAPI/Interface/Common/Interfaces/__init__.py
PySonataWebAPI/WebAPI/Interface/Common/Interfaces/IAgriculturalPromotionFundsController/__init__.py
PySonataWebAPI/WebAPI/Interface/Common/Interfaces/IAspectsClassificationController/__init__.py
PySonataWebAPI/WebAPI/Interface/Common/Interfaces/ICNCodesController/__init__.py
PySonataWebAPI/WebAPI/Interface/Common/Interfaces/ICountriesController/__init__.py
PySonataWebAPI/WebAPI/Interface/Common/Interfaces/ICurrenciesController/__init__.py
PySonataWebAPI/WebAPI/Interface/Common/Interfaces/ICurrencyRatesController/__init__.py
PySonataWebAPI/WebAPI/Interface/Common/Interfaces/IDepartmentsController/__init__.py
PySonataWebAPI/WebAPI/Interface/Common/Interfaces/IDocumentSeriesController/__init__.py
PySonataWebAPI/WebAPI/Interface/Common/Interfaces/IDocumentTypesController/__init__.py
PySonataWebAPI/WebAPI/Interface/Common/Interfaces/IPaymentFormsController/__init__.py
PySonataWebAPI/WebAPI/Interface/Common/Interfaces/IPaymentRegistriesController/__init__.py
PySonataWebAPI/WebAPI/Interface/Common/Interfaces/IPKWiUCodesController/__init__.py
PySonataWebAPI/WebAPI/Interface/Common/Interfaces/IPricesController/__init__.py
PySonataWebAPI/WebAPI/Interface/Common/Interfaces/IRegionsController/__init__.py
PySonataWebAPI/WebAPI/Interface/Common/Interfaces/IUnitsOfMeasurementController/__init__.py
PySonataWebAPI/WebAPI/Interface/Common/Interfaces/IVatRatesController/__init__.py
pysonatawebapi-1.0.1.dist-info/LICENSE
pysonatawebapi-1.0.1.dist-info/METADATA
pysonatawebapi-1.0.1.dist-info/WHEEL
pysonatawebapi-1.0.1.dist-info/RECORD
