Metadata-Version: 2.1
Name: PySonataWebAPI
Version: 1.0.1
Summary: Unofficial Symfonia WebAPI asynchronous client for python
Home-page: https://github.com/maku2903/PySonataWebAPI
License: Apache-2.0 license
Author: Maciej Pondo
Author-email: maciejpondo@gmail.com
Requires-Python: >=3.10,<4.0
Classifier: License :: Other/Proprietary License
Classifier: Programming Language :: Python :: 3
Classifier: Programming Language :: Python :: 3.10
Classifier: Programming Language :: Python :: 3.11
Requires-Dist: aiohttp (>=3.8,<4.0)
Requires-Dist: pydantic (>=2.0,<3.0)
Project-URL: Repository, https://github.com/maku2903/PySonataWebAPI
